NBRB_bki_xml_read/_init_.py
NBRB_bki_xml_read/common_tools.py
NBRB_bki_xml_read/individual_read.py
NBRB_bki_xml_read-0.0.5.dist-info/METADATA
NBRB_bki_xml_read-0.0.5.dist-info/WHEEL
NBRB_bki_xml_read-0.0.5.dist-info/top_level.txt
NBRB_bki_xml_read-0.0.5.dist-info/RECORD
